{
    "id": 131725589,
    "name": "Not Hard R V2",
    "author": "jiayefr",
    "creators": ["jiayefr"],
    "verifier": "Carmansaysman",
    "verification": "https://youtu.be/JIDqOrNobx4",
    "percentToQualify": 100,
    "hz": "240/360",
    "records": [
        {
            "user": "jiayefr",
            "link": "https://www.youtube.com/watch?v=epGcpObGQcU",
            "percent": 100,
            "hz": 240
        },
        {
            "user": "TraspGD",
            "link": "https://www.youtube.com/watch?v=u1tyii3qZvI",
            "percent": 100,
            "hz": 240
        },
        {
            "user": "Dan",
            "link": "https://youtu.be/5WqwRMnUyBg",
            "percent": 100,
            "hz": 60
        }
    ]
}
